Workbook

Sheet Guide
B2: Classera Onboarding Hub - content control
B3: onboarding.classera.com | edit this file, the site follows
B5: How to publish a change
B6: 1. Edit the Products or Tracks sheet below. Save.
B7: 2. On GitHub, open the site repository and click Add file > Upload files.
B8: 3. Drop this file in, renamed exactly onboarding-tracker.xlsx. It replaces the old one.
B9: 4. Click Commit changes. The site refreshes within about a minute.
B11: What each sheet controls
B12: Products One row per card in step 1. Order sets the position. Platform Host is where the track opens.
B13: Tracks One row per track card in step 3. The role chips in step 2 are built from this sheet.
B14: Lists The allowed values. Do not rename them.
B15: Summary Live counts. Read only.
... B27: Everything in this file is public once uploaded. Keep anything confidential out of it.

Sheet Products
A1: Site Key | B1: Order | C1: Product (EN) | D1: Product (AR) | E1: Description (EN) | F1: Description (AR) | G1: Icon | H1: Accent | I1: Platform Host | J1: Login Path | K1: Status
A2: lms | B2: 10 | C2: Learning Management System (LMS) | D2: نظام إدارة التعلم LMS | E2: Digital classes, assignments, assessment and parent communication. | F2: الفصول الرقمية، الواجبات، التقييم، والتواصل مع أولياء الأمور. | G2: lms | H2: cyan | I2: elearning.classera.com | J2: /login | K2: Live
A3: tms | B3: 20 | C3: Training Management System (TMS) | D3: نظام إدارة التدريب TMS | E3: Plan training programs, registration, attendance and certificates. | F3: تخطيط البرامج التدريبية، التسجيل، الحضور، والشهادات. | G3: tms | H3: blue | I3: leadxeratraining.classera.com | J3: /login | K3: Live
A4: erp | B4: 30 | C4: C-SmarX ERP | D4: نظام إدارة المؤسسة C-SmarX | E4: Admissions, finance, human resources and procurement. | F4: القبول والتسجيل، المالية، الموارد البشرية، والمشتريات. | G4: erp | H4: gold | I4: csmarxtraining.classera.com | J4: /login | K4: Live
A5: cpay | B5: 40 | C5: C-Pay | D5: C-Pay للمدفوعات | E5: Digital fee collection, installment plans and settlements. | F5: تحصيل الرسوم إلكترونياً، خطط التقسيط، والتسويات. | G5: pay | H5: green | K5: Live
A6: edumalls | B6: 50 | C6: Edumalls | D6: Edumalls | E6: The education marketplace: content, services and school products. | F6: المتجر التعليمي: المحتوى، الخدمات، والمنتجات المدرسية. | G6: mall | H6: gold | K6: Live
A7: cinspire | B7: 60 | C7: C-Inspire | D7: C-Inspire | E7: A gamified points system that rewards students for behavior, participation and achievement. | F7: نظام نقاط محفّز يكافئ الطلاب على السلوك والمشاركة والإنجاز. | G7: spark | H7: cyan | K7: Live

Sheet Tracks
A1: Site Key | B1: Product Key | C1: Role Key | D1: Role Order | E1: Role (EN) | F1: Role (AR) | G1: Track Order | H1: Track (EN) | I1: Track (AR) | J1: Description (EN) | K1: Description (AR) | L1: Level | M1: Modules | N1: Minutes | O1: Course Link | P1: Manual Link | Q1: Status | R1: Plan Link
A2: lms-01 | B2: lms | C2: teacher | D2: 10 | E2: Teacher | F2: معلم | G2: 10 | H2: LMS Essentials for Teachers | I2: أساسيات LMS للمعلم | J2: Build your class, upload content, schedule sessions and track attendance. | K2: إنشاء الفصل، رفع المحتوى، جدولة الحصص، ومتابعة الحضور. | L2: Essential | M2: 1 | N2: 55 | O2: https://elearning.classera.com/lectures-list/?course_title=Teachers%20Account%20|%20AY26&course_type=2&c=eyJjb3Vyc2VfaWQiOiIxMjIzNjEifQ | P2: https://manual.classera.com/docs-category/teacher-account/ | Q2: Live
A3: lms-02 | B3: lms | C3: teacher | D3: 10 | E3: Teacher | F3: معلم | G3: 20 | H3: Assessment and Grading | I3: التقييم والدرجات | J3: Question banks, online exams, auto-grading and performance reports. | K3: بنوك الأسئلة، الاختبارات الإلكترونية، الرصد التلقائي، وتقارير الأداء. | L3: Core | M3: 1 | N3: 90 | P3: https://manual.classera.com/docs-category/grade-management-teacher/ | Q3: Live
A4: lms-03 | B4: lms | C4: leader | D4: 20 | E4: School Leader | F4: قائد مدرسة | G4: 10 | H4: Leadership Dashboards | I4: لوحات المتابعة للقيادة المدرسية | J4: Read usage KPIs, monitor teacher activity and make data-driven decisions. | K4: قراءة مؤشرات الاستخدام، متابعة أداء المعلمين، واتخاذ قرار مبني على البيانات. | L4: Core | M4: 1 | N4: 75 | O4: https://elearning.classera.com/lectures-list/?course_title=Manager%20Account%20|%20AY26&course_type=2&c=eyJjb3Vyc2VfaWQiOiIxMjI0MDcifQ | P4: https://manual.classera.com/docs-category/manager-account/ | Q4: Live
A5: lms-04 | B5: lms | C5: student | D5: 30 | E5: Student | F5: طالب | G5: 10 | H5: Student Quick Start | I5: دليل الطالب للبدء | J5: Sign in, assignments, quizzes and reaching your teacher. | K5: الدخول، الواجبات، الاختبارات، والتواصل مع المعلم. | L5: Essential | P5: https://manual.classera.com/docs-category/student-account/ | Q5: Coming soon
A6: lms-05 | B6: lms | C6: parent | D6: 40 | E6: Parent | F6: ولي أمر | G6: 10 | H6: Parent Quick Start | I6: دليل ولي الأمر | J6: Follow attendance, grades and school communication from the app. | K6: متابعة الحضور والدرجات والتواصل مع المدرسة من التطبيق. | L6: Essential | P6: https://manual.classera.com/docs-category/parent-account/ | Q6: Coming soon
A7: lms-06 | B7: lms | C7: itadmin | D7: 50 | E7: System Admin | F7: مسؤول النظام | G7: 10 | H7: Platform Setup and Administration | I7: إعداد وإدارة المنصة | J7: Account structure, roles and permissions, bulk import and integrations. | K7: هيكلة الحسابات، الأدوار والصلاحيات، الاستيراد الجماعي، والتكاملات. | L7: Advanced | M7: 1 | N7: 90 | O7: https://elearning.classera.com/lectures-list/?course_title=Administrator%20Account%20|%20AY26&course_type=2&c=eyJjb3Vyc2VfaWQiOiIxMjIzNjIifQ | P7: https://manual.classera.com/docs-category/administrator-account/ | Q7: Live
A8: lms-07 | B8: lms | C8: tsupervisor | D8: 22 | E8: Teacher Supervisor | F8: مشرف تربوي | G8: 10 | H8: Supervising Teaching Quality | I8: متابعة جودة التدريس | J8: Follow teacher activity, review lessons and assessments, and give data-based feedback. | K8: متابعة نشاط المعلمين، مراجعة الدروس والتقييمات، وتقديم تغذية راجعة مبنية على البيانات. | L8: Core | Q8: Coming soon
A9: lms-08 | B9: lms | C9: floorsup | D9: 24 | E9: Floor Supervisor & Advisor | F9: مشرف الدور والمرشد الطلابي | G9: 10 | H9: Student Follow-up and Guidance | I9: متابعة الطلاب والإرشاد | J9: Track attendance and behavior, record student notes and communicate with parents. | K9: متابعة الحضور والسلوك، تسجيل ملاحظات الطلاب، والتواصل مع أولياء الأمور. | L9: Essential | Q9: Coming soon
A10: lms-09 | B10: lms | C10: teacher | D10: 10 | E10: Teacher | F10: معلم | G10: 30 | H10: Classera Teacher Accreditation | I10: اعتماد المعلم من كلاسيرا | J10: Get accredited from User to Expert level: review the criteria, apply, sit the exam and earn a 3-year certificate. | K10: احصل على اعتمادك من مستوى مستخدم إلى خبير: راجع المعايير، قدّم طلبك، اجتز الاختبار، واحصل على شهادة صالحة لثلاث سنوات. | L10: Advanced | O10: https://accreditation.classera.com/ | Q10: Live | R10: https://plans.classera.com/#acc
A11: lms-10 | B11: lms | C11: itadmin | D11: 50 | E11: System Admin | F11: مسؤول النظام | G11: 20 | H11: System Manager Accreditation | I11: اعتماد مدير النظام | J11: Get accredited as a System Manager, from Practitioner to Professional level, through criteria review, application and exam. | K11: احصل على اعتماد مدير النظام من مستوى ممارس إلى محترف عبر مراجعة المعايير، تقديم الطلب، واجتياز الاختبار. | L11: Advanced | O11: https://accreditation.classera.com/ | Q11: Live | R11: https://plans.classera.com/#acc
A12: tms-01 | B12: tms | C12: trmanager | D12: 10 | E12: Training Manager | F12: مدير التدريب | G12: 10 | H12: Academy Style & Settings | I12: نمط الأكاديمية وإعداداتها | J12: Set up your academy's look and feel and its core platform settings. | K12: تجهيز الهوية البصرية للأكاديمية وضبط إعدادات المنصة الأساسية. | L12: Essential | O12: https://leadxeratraining.classera.com/lectures-list/?course_title=TMS%20|%20Academy%20Style%20%26%20Settings&course_type=1&c=eyJjb3Vyc2VfaWQiOiIxMjgzMTkifQ | P12: https://usermanual.leadxera.com/docs/styles-and-academy-settings/ | Q12: Live
A13: tms-02 | B13: tms | C13: trmanager | D13: 10 | E13: Training Manager | F13: مدير التدريب | G13: 20 | H13: User Management | I13: إدارة المستخدمين | J13: Add and manage corporates, trainers and trainees, and control their access. | K13: إضافة وإدارة الجهات المؤسسية والمدربين والمتدربين والتحكم في صلاحياتهم. | L13: Essential | O13: https://leadxeratraining.classera.com/lectures-list/?course_title=TMS%20|%20User%20Management%20(Instance%201)&course_type=1&c=eyJjb3Vyc2VfaWQiOiIxMjgzMTcifQ | P13: https://usermanual.leadxera.com/docs/manage-users-2/ | Q13: Live
A14: tms-03 | B14: tms | C14: instructor | D14: 20 | E14: Trainer | F14: مدرب | G14: 10 | H14: Trainer Guide | I14: دليل المدرب | J14: Run the session, mark attendance, deliver materials and assess trainees. | K14: إدارة الجلسة، رصد الحضور، تسليم المواد، وتقييم المتدربين. | L14: Essential | M14: 1 | N14: 60 | P14: https://usermanual.leadxera.com/docs-category/trainer/ | Q14: Coming soon
A15: tms-04 | B15: tms | C15: trainee | D15: 30 | E15: Trainee | F15: متدرب | G15: 10 | H15: Trainee Guide | I15: دليل المتدرب | J15: Enroll in programs, track progress and download your certificate. | K15: التسجيل في البرامج، متابعة التقدم، وتحميل الشهادة. | L15: Essential | M15: 1 | N15: 60 | P15: https://usermanual.leadxera.com/docs-category/trainees/ | Q15: Coming soon
A16: tms-05 | B16: tms | C16: corporate | D16: 40 | E16: Corporate | F16: جهة مؤسسية | G16: 10 | H16: Managing Your People | I16: إدارة منسوبيك | J16: Enroll your team, follow progress and pull enrollment reports. | K16: تسجيل فريقك، متابعة التقدم، واستخراج تقارير التسجيل. | L16: Core | M16: 1 | N16: 60 | P16: https://usermanual.leadxera.com/docs-category/corporate/ | Q16: Coming soon
A17: erp-01 | B17: erp | C17: finance | D17: 10 | E17: Finance Manager | F17: مدير مالي | G17: 10 | H17: Core Finance Cycle | I17: الدورة المالية الأساسية | J17: Tuition fees, invoicing, collections and financial reporting. | K17: الرسوم الدراسية، الفوترة، التحصيل، والتقارير المالية. | L17: Essential | M17: 1 | N17: 60 | Q17: Coming soon
A18: erp-02 | B18: erp | C18: finance | D18: 10 | E18: Finance Manager | F18: مدير مالي | G18: 20 | H18: Budgeting and Financial Analysis | I18: الموازنات والتحليل المالي | J18: Build budgets, compare plan vs actual and analyze variances. | K18: بناء الموازنة، مقارنة المخطط بالفعلي، وتحليل الانحرافات. | L18: Advanced | M18: 1 | N18: 60 | Q18: Coming soon
A19: erp-03 | B19: erp | C19: registrar | D19: 20 | E19: Registrar | F19: شؤون الطلاب | G19: 10 | H19: Admissions and Registration | I19: القبول والتسجيل | J19: Student file, enrollment, class allocation and official documents. | K19: ملف الطالب، التسجيل، توزيع الفصول، والوثائق الرسمية. | L19: Essential | M19: 1 | N19: 60 | Q19: Coming soon
A20: erp-04 | B20: erp | C20: hrofficer | D20: 30 | E20: HR Officer | F20: موظف موارد بشرية | G20: 10 | H20: HR Operations | I20: إدارة شؤون الموظفين | J20: Employee file, attendance and leave, and payroll. | K20: ملف الموظف، الحضور والإجازات، والرواتب. | L20: Core | M20: 1 | N20: 60 | P20: https://usermanual.csmarx.com/docs-category/human-resources/ | Q20: Coming soon
A21: erp-05 | B21: erp | C21: procure | D21: 40 | E21: Procurement | F21: المشتريات والمخازن | G21: 10 | H21: Procurement and Inventory | I21: المشتريات والمخزون | J21: Purchase orders, vendors, receiving and asset inventory. | K21: أوامر الشراء، الموردون، الاستلام، وجرد الأصول. | L21: Core | M21: 1 | N21: 60 | Q21: Coming soon
A22: erp-06 | B22: erp | C22: itadmin | D22: 50 | E22: System Admin | F22: مسؤول النظام | G22: 10 | H22: System Setup and Permissions | I22: إعداد النظام والصلاحيات | J22: Org structure, approval cycles and module-level permissions. | K22: الهيكل التنظيمي، دورات الاعتماد، والصلاحيات على مستوى الوحدة. | L22: Advanced | M22: 1 | N22: 60 | Q22: Coming soon
A23: cpay-01 | B23: cpay | C23: finofficer | D23: 10 | E23: Finance Officer | F23: موظف مالي | G23: 10 | H23: Activating Digital Collection | I23: تفعيل التحصيل الإلكتروني | J23: Link fees, issue payment links and run daily follow-up. | K23: ربط الرسوم، إصدار روابط الدفع، والمتابعة اليومية. | L23: Essential | M23: 1 | N23: 60 | P23: https://manual.classera.com/docs-category/school-accountant/ | Q23: Coming soon
A24: cpay-02 | B24: cpay | C24: finofficer | D24: 10 | E24: Finance Officer | F24: موظف مالي | G24: 20 | H24: Reconciliation and Reporting | I24: التسويات والتقارير | J24: Match payments, bank settlement and collection reports. | K24: مطابقة المدفوعات، التسويات البنكية، وتقارير التحصيل. | L24: Core | M24: 1 | N24: 60 | Q24: Coming soon
A25: cpay-03 | B25: cpay | C25: cashier | D25: 20 | E25: Cashier | F25: أمين صندوق | G25: 10 | H25: Cashier Guide | I25: دليل أمين الصندوق | J25: On-site payments, receipts and refunds. | K25: الدفع الحضوري، الإيصالات، والاسترجاع. | L25: Essential | M25: 1 | N25: 60 | Q25: Coming soon
A26: cpay-04 | B26: cpay | C26: parent | D26: 30 | E26: Parent | F26: ولي أمر | G26: 10 | H26: Paying as a Parent | I26: الدفع لولي الأمر | J26: View your invoice, pay online and use installment plans. | K26: عرض الفاتورة، الدفع الإلكتروني، وخطط التقسيط. | L26: Essential | M26: 1 | N26: 60 | P26: https://manual.classera.com/docs-category/c-pay-parent/ | Q26: Coming soon
A27: edu-01 | B27: edumalls | C27: storemgr | D27: 10 | E27: Store Manager | F27: مدير المتجر | G27: 10 | H27: Setting Up Your Store | I27: تجهيز المتجر | J27: Catalog, pricing, offers and order management. | K27: الكتالوج، التسعير، العروض، وإدارة الطلبات. | L27: Essential | M27: 1 | N27: 60 | Q27: Coming soon
A28: edu-02 | B28: edumalls | C28: publisher | D28: 20 | E28: Content Publisher | F28: ناشر محتوى | G28: 10 | H28: Publishing Educational Content | I28: نشر المحتوى التعليمي | J28: Upload content, quality standards, rights and revenue share. | K28: رفع المحتوى، معايير الجودة، والحقوق ومشاركة الإيراد. | L28: Core | M28: 1 | N28: 60 | Q28: Coming soon
A29: edu-03 | B29: edumalls | C29: storemgr | D29: 10 | E29: Store Manager | F29: مدير المتجر | G29: 20 | H29: Sales Analytics | I29: تحليل المبيعات | J29: Product performance, conversion rate and pricing decisions. | K29: أداء المنتجات، معدل التحويل، وقرارات التسعير. | L29: Advanced | M29: 1 | N29: 60 | Q29: Coming soon
A30: edu-04 | B30: edumalls | C30: buyer | D30: 30 | E30: Buyer / Parent | F30: مشتري / ولي أمر | G30: 10 | H30: Buyer Guide | I30: دليل الشراء | J30: Search, order, pay and track. | K30: البحث، الطلب، الدفع، والمتابعة. | L30: Essential | M30: 1 | N30: 60 | Q30: Coming soon
A31: cin-01 | B31: cinspire | C31: activity | D31: 10 | E31: Activity Officer | F31: مسؤول الأنشطة | G31: 10 | H31: Setting Up the Points System | I31: إعداد نظام النقاط | J31: Define point categories, values, levels and the reward catalog for your school. | K31: تحديد فئات النقاط وقيمها ومستوياتها وقائمة المكافآت الخاصة بمدرستك. | L31: Core | M31: 1 | N31: 60 | P31: https://manual.classera.com/docs-category/c-inspire-awards-activity-officer/ | Q31: Coming soon
A32: cin-02 | B32: cinspire | C32: activity | D32: 10 | E32: Activity Officer | F32: مسؤول الأنشطة | G32: 20 | H32: Rewards, Badges and Leaderboards | I32: المكافآت والشارات ولوحات الصدارة | J32: Design reward tiers, publish leaderboards and run seasonal point campaigns. | K32: تصميم مستويات المكافآت، نشر لوحات الصدارة، وإطلاق حملات نقاط موسمية. | L32: Advanced | M32: 1 | N32: 60 | Q32: Coming soon
A33: cin-03 | B33: cinspire | C33: teacher | D33: 20 | E33: Teacher | F33: معلم | G33: 10 | H33: Awarding Points in Class | I33: منح النقاط داخل الفصل | J33: Give and withdraw points, use quick actions, and keep awarding fair and consistent. | K33: منح النقاط وسحبها، استخدام الإجراءات السريعة، والحفاظ على عدالة المنح واتساقه. | L33: Essential | M33: 1 | N33: 60 | P33: https://manual.classera.com/docs-category/c-inspire/ | Q33: Coming soon
A34: cin-04 | B34: cinspire | C34: student | D34: 30 | E34: Student | F34: طالب | G34: 10 | H34: Earning and Spending Your Points | I34: اكسب نقاطك واستبدلها | J34: Track your balance, climb the leaderboard, and redeem points for rewards and badges. | K34: تابع رصيدك، تقدّم في لوحة الصدارة، واستبدل نقاطك بالمكافآت والشارات. | L34: Essential | M34: 1 | N34: 60 | P34: https://manual.classera.com/docs-category/c-inspire-awards-and-scores-student/ | Q34: Coming soon
A35: cin-05 | B35: cinspire | C35: parent | D35: 40 | E35: Parent | F35: ولي أمر | G35: 10 | H35: Following Your Child's Points | I35: متابعة نقاط أبنائك | J35: See points earned, the reasons behind them, and your child's standing. | K35: اطّلع على النقاط المكتسبة وأسبابها وترتيب ابنك. | L35: Essential | M35: 1 | N35: 60 | P35: https://manual.classera.com/docs-category/c-inspire-awards-parent/ | Q35: Coming soon
A36: tms-06 | B36: tms | C36: trmanager | D36: 10 | E36: Training Manager | F36: مدير التدريب | G36: 30 | H36: Course Design & Content | I36: تصميم الدورات والمحتوى | J36: Create courses and build their content, sessions and assessments. | K36: إنشاء الدورات وبناء محتواها وجلساتها وتقييماتها. | L36: Core | O36: https://leadxeratraining.classera.com/lectures-list/?course_title=TMS|%20Course%20Design%20%26%20Content%20%20|%20Content&course_type=1&c=eyJjb3Vyc2VfaWQiOiIxMjgzMTgifQ | P36: https://usermanual.leadxera.com/docs/managing-content-2/ | Q36: Live
A37: tms-07 | B37: tms | C37: trmanager | D37: 10 | E37: Training Manager | F37: مدير التدريب | G37: 40 | H37: Follow Up & Reporting Tools | I37: أدوات المتابعة والتقارير | J37: Track learner progress with progress, enrollment and course statistics reports. | K37: متابعة تقدم المتدربين عبر تقارير التقدم والتسجيل وإحصائيات الدورات. | L37: Core | O37: https://leadxeratraining.classera.com/lectures-list/?course_title=TMS%20|%20%20Follow%20Up%20%26%20Reporting%20Tools&course_type=1&c=eyJjb3Vyc2VfaWQiOiIxMjgzMTYifQ | P37: https://usermanual.leadxera.com/docs/comprehensive-progress-report/ | Q37: Live

Sheet Lists
A1: Icon | B1: Accent | C1: Level | D1: Status
A2: lms | B2: cyan | C2: Essential | D2: Live
A3: tms | B3: blue | C3: Core | D3: Coming soon
A4: erp | B4: gold | C4: Advanced | D4: Hidden
A5: pay | B5: green
A6: mall
A7: spark
A8: book
A9: chart

Sheet Summary
B2: Coverage at a glance
B3: Counts update automatically from the Tracks sheet.
B5: Product | C5: Status | D5: Roles | E5: Tracks | F5: Live tracks | G5: Course links set | H5: Manual links set
B6: Learning Management System (LMS) | C6: =INDEX(Products!$K$2:$K$7,MATCH("lms",Products!$A$2:$A$7,0)) | D6: =SUMPRODUCT((Tracks!$B$2:$B$200="lms")/COUNTIFS(Tracks!$B$2:$B$200,Tracks!$B$2:$B$200&"",Tracks!$C$2:$C$200,Tracks!$C$2:$C$200&"")) | E6: =COUNTIF(Tracks!$B$2:$B$200,"lms") | F6: =COUNTIFS(Tracks!$B$2:$B$200,"lms",Tracks!$Q$2:$Q$200,"Live") | G6: =COUNTIFS(Tracks!$B$2:$B$200,"lms",Tracks!$O$2:$O$200,"<>") | H6: =COUNTIFS(Tracks!$B$2:$B$200,"lms",Tracks!$P$2:$P$200,"<>")
B7: Training Management System (TMS) | C7: =INDEX(Products!$K$2:$K$7,MATCH("tms",Products!$A$2:$A$7,0)) | D7: =SUMPRODUCT((Tracks!$B$2:$B$200="tms")/COUNTIFS(Tracks!$B$2:$B$200,Tracks!$B$2:$B$200&"",Tracks!$C$2:$C$200,Tracks!$C$2:$C$200&"")) | E7: =COUNTIF(Tracks!$B$2:$B$200,"tms") | F7: =COUNTIFS(Tracks!$B$2:$B$200,"tms",Tracks!$Q$2:$Q$200,"Live") | G7: =COUNTIFS(Tracks!$B$2:$B$200,"tms",Tracks!$O$2:$O$200,"<>") | H7: =COUNTIFS(Tracks!$B$2:$B$200,"tms",Tracks!$P$2:$P$200,"<>")
B8: C-SmarX ERP | C8: =INDEX(Products!$K$2:$K$7,MATCH("erp",Products!$A$2:$A$7,0)) | D8: =SUMPRODUCT((Tracks!$B$2:$B$200="erp")/COUNTIFS(Tracks!$B$2:$B$200,Tracks!$B$2:$B$200&"",Tracks!$C$2:$C$200,Tracks!$C$2:$C$200&"")) | E8: =COUNTIF(Tracks!$B$2:$B$200,"erp") | F8: =COUNTIFS(Tracks!$B$2:$B$200,"erp",Tracks!$Q$2:$Q$200,"Live") | G8: =COUNTIFS(Tracks!$B$2:$B$200,"erp",Tracks!$O$2:$O$200,"<>") | H8: =COUNTIFS(Tracks!$B$2:$B$200,"erp",Tracks!$P$2:$P$200,"<>")
B9: C-Pay | C9: =INDEX(Products!$K$2:$K$7,MATCH("cpay",Products!$A$2:$A$7,0)) | D9: =SUMPRODUCT((Tracks!$B$2:$B$200="cpay")/COUNTIFS(Tracks!$B$2:$B$200,Tracks!$B$2:$B$200&"",Tracks!$C$2:$C$200,Tracks!$C$2:$C$200&"")) | E9: =COUNTIF(Tracks!$B$2:$B$200,"cpay") | F9: =COUNTIFS(Tracks!$B$2:$B$200,"cpay",Tracks!$Q$2:$Q$200,"Live") | G9: =COUNTIFS(Tracks!$B$2:$B$200,"cpay",Tracks!$O$2:$O$200,"<>") | H9: =COUNTIFS(Tracks!$B$2:$B$200,"cpay",Tracks!$P$2:$P$200,"<>")
B10: Edumalls | C10: =INDEX(Products!$K$2:$K$7,MATCH("edumalls",Products!$A$2:$A$7,0)) | D10: =SUMPRODUCT((Tracks!$B$2:$B$200="edumalls")/COUNTIFS(Tracks!$B$2:$B$200,Tracks!$B$2:$B$200&"",Tracks!$C$2:$C$200,Tracks!$C$2:$C$200&"")) | E10: =COUNTIF(Tracks!$B$2:$B$200,"edumalls") | F10: =COUNTIFS(Tracks!$B$2:$B$200,"edumalls",Tracks!$Q$2:$Q$200,"Live") | G10: =COUNTIFS(Tracks!$B$2:$B$200,"edumalls",Tracks!$O$2:$O$200,"<>") | H10: =COUNTIFS(Tracks!$B$2:$B$200,"edumalls",Tracks!$P$2:$P$200,"<>")
B11: C-Inspire | C11: =INDEX(Products!$K$2:$K$7,MATCH("cinspire",Products!$A$2:$A$7,0)) | D11: =SUMPRODUCT((Tracks!$B$2:$B$200="cinspire")/COUNTIFS(Tracks!$B$2:$B$200,Tracks!$B$2:$B$200&"",Tracks!$C$2:$C$200,Tracks!$C$2:$C$200&"")) | E11: =COUNTIF(Tracks!$B$2:$B$200,"cinspire") | F11: =COUNTIFS(Tracks!$B$2:$B$200,"cinspire",Tracks!$Q$2:$Q$200,"Live") | G11: =COUNTIFS(Tracks!$B$2:$B$200,"cinspire",Tracks!$O$2:$O$200,"<>") | H11: =COUNTIFS(Tracks!$B$2:$B$200,"cinspire",Tracks!$P$2:$P$200,"<>")
B12: Total | D12: =SUM(D6:D11) | E12: =SUM(E6:E11) | F12: =SUM(F6:F11) | G12: =SUM(G6:G11) | H12: =SUM(H6:H11)
